humiris_ai/__init__.py
humiris_ai/advanced-mixtuning.py
humiris_ai/advanced_mixtuning.py
humiris_ai/basic-mixtuning.py
humiris_ai/basic_mixtuning.py
package/__init__.py
package/advanced-mixtuning.py
package/basic-mixtuning.py
humiris_ai-1.0.11.dist-info/LICENSE
humiris_ai-1.0.11.dist-info/METADATA
humiris_ai-1.0.11.dist-info/WHEEL
humiris_ai-1.0.11.dist-info/top_level.txt
humiris_ai-1.0.11.dist-info/RECORD
