Metadata-Version: 2.2
Name: humiris_ai
Version: 1.0.11
Summary: Humiris AI is a library that allows developers to seamlessly integrate Mixture of AI Basic and Advanced into their applications.
Home-page: https://github.com/joeai-tech-org/humiris-pip-package
Author: Hilario Houmey
Author-email: h.hilario@humiris.ai
Classifier: Programming Language :: Python :: 3
Classifier: License :: OSI Approved :: MIT License
Classifier: Operating System :: OS Independent
Requires-Python: >=3.6
License-File: LICENSE
Requires-Dist: requests>=2.20.0
Requires-Dist: setuptools>=40.0.0
Requires-Dist: pydantic>=2.20.1
Dynamic: author
Dynamic: author-email
Dynamic: classifier
Dynamic: description
Dynamic: description-content-type
Dynamic: home-page
Dynamic: requires-dist
Dynamic: requires-python
Dynamic: summary
